{
  "idea_id": "idea-saas-pricing-intelligence",
  "timestamp": "2026-03-10T07:41:24.711039+00:00",
  "analyses_generated": 20,
  "revenue": 153.1267,
  "cost": 0.1,
  "projected_monthly_revenue": 4593.8,
  "results": [
    {
      "product_name": "Enterprise CRM",
      "recommended_price": 302.63,
      "confidence": 0.7153,
      "tier": "enterprise",
      "segment": "enterprise",
      "conversion_probability": 0.35,
      "expected_revenue": 11.655
    },
    {
      "product_name": "API Management Platform",
      "recommended_price": 352.08,
      "confidence": 0.7001,
      "tier": "enterprise",
      "segment": "enterprise",
      "conversion_probability": 0.35,
      "expected_revenue": 11.655
    },
    {
      "product_name": "Identity Management",
      "recommended_price": 326.8,
      "confidence": 0.7014,
      "tier": "enterprise",
      "segment": "enterprise",
      "conversion_probability": 0.35,
      "expected_revenue": 11.655
    },
    {
      "product_name": "Customer Data Platform",
      "recommended_price": 392.1,
      "confidence": 0.681,
      "tier": "enterprise",
      "segment": "enterprise",
      "conversion_probability": 0.35,
      "expected_revenue": 11.655
    },
    {
      "product_name": "HR Management System",
      "recommended_price": 309.73,
      "confidence": 0.7798,
      "tier": "enterprise",
      "segment": "enterprise",
      "conversion_probability": 0.35,
      "expected_revenue": 11.655
    },
    {
      "product_name": "Cybersecurity Platform",
      "recommended_price": 381.07,
      "confidence": 0.752,
      "tier": "enterprise",
      "segment": "enterprise",
      "conversion_probability": 0.35,
      "expected_revenue": 11.655
    },
    {
      "product_name": "Data Warehouse Solution",
      "recommended_price": 458.64,
      "confidence": 0.7261,
      "tier": "enterprise",
      "segment": "enterprise",
      "conversion_probability": 0.35,
      "expected_revenue": 11.655
    },
    {
      "product_name": "Security Information Manager",
      "recommended_price": 335.34,
      "confidence": 0.7128,
      "tier": "enterprise",
      "segment": "enterprise",
      "conversion_probability": 0.35,
      "expected_revenue": 11.655
    },
    {
      "product_name": "Business Intelligence Tool",
      "recommended_price": 333.17,
      "confidence": 0.7935,
      "tier": "enterprise",
      "segment": "enterprise",
      "conversion_probability": 0.35,
      "expected_revenue": 11.655
    },
    {
      "product_name": "Cloud Project Management",
      "recommended_price": 279.86,
      "confidence": 0.6897,
      "tier": "enterprise",
      "segment": "enterprise",
      "conversion_probability": 0.35,
      "expected_revenue": 11.655
    },
    {
      "product_name": "Contract Management",
      "recommended_price": 312.92,
      "confidence": 0.6707,
      "tier": "enterprise",
      "segment": "enterprise",
      "conversion_probability": 0.35,
      "expected_revenue": 11.655
    },
    {
      "product_name": "Cloud Migration Tool",
      "recommended_price": 368.29,
      "confidence": 0.6787,
      "tier": "enterprise",
      "segment": "enterprise",
      "conversion_probability": 0.35,
      "expected_revenue": 11.655
    },
    {
      "product_name": "Marketing Platform",
      "recommended_price": 215.02,
      "confidence": 0.7809,
      "tier": "growth",
      "segment": "mid-market",
      "conversion_probability": 0.25,
      "expected_revenue": 1.6583
    },
    {
      "product_name": "Video Conferencing Pro",
      "recommended_price": 202.42,
      "confidence": 0.702,
      "tier": "growth",
      "segment": "mid-market",
      "conversion_probability": 0.25,
      "expected_revenue": 1.6583
    },
    {
      "product_name": "Email Marketing Suite",
      "recommended_price": 180.7,
      "confidence": 0.7644,
      "tier": "growth",
      "segment": "mid-market",
      "conversion_probability": 0.25,
      "expected_revenue": 1.6583
    },
    {
      "product_name": "Learning Management System",
      "recommended_price": 201.24,
      "confidence": 0.7929,
      "tier": "growth",
      "segment": "mid-market",
      "conversion_probability": 0.25,
      "expected_revenue": 1.6583
    },
    {
      "product_name": "E-commerce Platform",
      "recommended_price": 224.73,
      "confidence": 0.7111,
      "tier": "growth",
      "segment": "mid-market",
      "conversion_probability": 0.25,
      "expected_revenue": 1.6583
    },
    {
      "product_name": "DevOps Automation Tool",
      "recommended_price": 238.45,
      "confidence": 0.7061,
      "tier": "growth",
      "segment": "mid-market",
      "conversion_probability": 0.25,
      "expected_revenue": 1.6583
    },
    {
      "product_name": "IT Service Management",
      "recommended_price": 238.82,
      "confidence": 0.7478,
      "tier": "growth",
      "segment": "mid-market",
      "conversion_probability": 0.25,
      "expected_revenue": 1.6583
    },
    {
      "product_name": "Product Analytics Platform",
      "recommended_price": 199.12,
      "confidence": 0.7864,
      "tier": "growth",
      "segment": "mid-market",
      "conversion_probability": 0.25,
      "expected_revenue": 1.6583
    }
  ],
  "dry_run": false
}
