{
  "idea_id": "idea-saas-pricing-intelligence",
  "timestamp": "2026-03-10T02:09:13.370987+00:00",
  "analyses_generated": 20,
  "revenue": 83.6817,
  "cost": 0.1,
  "projected_monthly_revenue": 2510.45,
  "results": [
    {
      "product_name": "Enterprise CRM",
      "recommended_price": 303.84,
      "confidence": 0.7505,
      "tier": "enterprise",
      "segment": "enterprise",
      "conversion_probability": 0.35,
      "expected_revenue": 11.655
    },
    {
      "product_name": "API Management Platform",
      "recommended_price": 381.97,
      "confidence": 0.6963,
      "tier": "enterprise",
      "segment": "enterprise",
      "conversion_probability": 0.35,
      "expected_revenue": 11.655
    },
    {
      "product_name": "Identity Management",
      "recommended_price": 328.79,
      "confidence": 0.7728,
      "tier": "enterprise",
      "segment": "enterprise",
      "conversion_probability": 0.35,
      "expected_revenue": 11.655
    },
    {
      "product_name": "Customer Data Platform",
      "recommended_price": 385.06,
      "confidence": 0.7364,
      "tier": "enterprise",
      "segment": "enterprise",
      "conversion_probability": 0.35,
      "expected_revenue": 11.655
    },
    {
      "product_name": "HR Management System",
      "recommended_price": 303.24,
      "confidence": 0.7762,
      "tier": "enterprise",
      "segment": "enterprise",
      "conversion_probability": 0.35,
      "expected_revenue": 11.655
    },
    {
      "product_name": "Cloud Project Management",
      "recommended_price": 307.09,
      "confidence": 0.7955,
      "tier": "enterprise",
      "segment": "enterprise",
      "conversion_probability": 0.35,
      "expected_revenue": 11.655
    },
    {
      "product_name": "Marketing Platform",
      "recommended_price": 213.63,
      "confidence": 0.7758,
      "tier": "growth",
      "segment": "mid-market",
      "conversion_probability": 0.25,
      "expected_revenue": 1.6583
    },
    {
      "product_name": "Video Conferencing Pro",
      "recommended_price": 192.54,
      "confidence": 0.7934,
      "tier": "growth",
      "segment": "mid-market",
      "conversion_probability": 0.25,
      "expected_revenue": 1.6583
    },
    {
      "product_name": "Email Marketing Suite",
      "recommended_price": 163.15,
      "confidence": 0.773,
      "tier": "growth",
      "segment": "mid-market",
      "conversion_probability": 0.25,
      "expected_revenue": 1.6583
    },
    {
      "product_name": "Learning Management System",
      "recommended_price": 237.76,
      "confidence": 0.6785,
      "tier": "growth",
      "segment": "mid-market",
      "conversion_probability": 0.25,
      "expected_revenue": 1.6583
    },
    {
      "product_name": "E-commerce Platform",
      "recommended_price": 236.56,
      "confidence": 0.7686,
      "tier": "growth",
      "segment": "mid-market",
      "conversion_probability": 0.25,
      "expected_revenue": 1.6583
    },
    {
      "product_name": "Team Collaboration Tool",
      "recommended_price": 154.48,
      "confidence": 0.7189,
      "tier": "growth",
      "segment": "smb",
      "conversion_probability": 0.15,
      "expected_revenue": 0.995
    },
    {
      "product_name": "Accounting Software",
      "recommended_price": 143.05,
      "confidence": 0.7875,
      "tier": "growth",
      "segment": "smb",
      "conversion_probability": 0.15,
      "expected_revenue": 0.995
    },
    {
      "product_name": "Inventory Management",
      "recommended_price": 149.27,
      "confidence": 0.7997,
      "tier": "growth",
      "segment": "smb",
      "conversion_probability": 0.15,
      "expected_revenue": 0.995
    },
    {
      "product_name": "Point of Sale System",
      "recommended_price": 150.11,
      "confidence": 0.6766,
      "tier": "growth",
      "segment": "smb",
      "conversion_probability": 0.15,
      "expected_revenue": 0.995
    },
    {
      "product_name": "Help Desk Software",
      "recommended_price": 102.91,
      "confidence": 0.7654,
      "tier": "starter",
      "segment": "smb",
      "conversion_probability": 0.15,
      "expected_revenue": 0.245
    },
    {
      "product_name": "Social Media Scheduler",
      "recommended_price": 124.09,
      "confidence": 0.7319,
      "tier": "starter",
      "segment": "smb",
      "conversion_probability": 0.15,
      "expected_revenue": 0.245
    },
    {
      "product_name": "No-Code Database",
      "recommended_price": 118.67,
      "confidence": 0.6746,
      "tier": "growth",
      "segment": "startup",
      "conversion_probability": 0.1,
      "expected_revenue": 0.6633
    },
    {
      "product_name": "Startup Analytics",
      "recommended_price": 130.15,
      "confidence": 0.6894,
      "tier": "starter",
      "segment": "startup",
      "conversion_probability": 0.1,
      "expected_revenue": 0.1633
    },
    {
      "product_name": "Landing Page Builder",
      "recommended_price": 111.24,
      "confidence": 0.6977,
      "tier": "starter",
      "segment": "startup",
      "conversion_probability": 0.1,
      "expected_revenue": 0.1633
    }
  ],
  "dry_run": false
}
