{
  "idea_id": "idea-saas-pricing-intelligence",
  "timestamp": "2026-03-10T05:18:17.341806+00:00",
  "analyses_generated": 20,
  "revenue": 153.1267,
  "cost": 0.1,
  "projected_monthly_revenue": 4593.8,
  "results": [
    {
      "product_name": "Enterprise CRM",
      "recommended_price": 321.75,
      "confidence": 0.7971,
      "tier": "enterprise",
      "segment": "enterprise",
      "conversion_probability": 0.35,
      "expected_revenue": 11.655
    },
    {
      "product_name": "API Management Platform",
      "recommended_price": 346.93,
      "confidence": 0.7594,
      "tier": "enterprise",
      "segment": "enterprise",
      "conversion_probability": 0.35,
      "expected_revenue": 11.655
    },
    {
      "product_name": "Identity Management",
      "recommended_price": 324.82,
      "confidence": 0.6787,
      "tier": "enterprise",
      "segment": "enterprise",
      "conversion_probability": 0.35,
      "expected_revenue": 11.655
    },
    {
      "product_name": "Customer Data Platform",
      "recommended_price": 396.81,
      "confidence": 0.7343,
      "tier": "enterprise",
      "segment": "enterprise",
      "conversion_probability": 0.35,
      "expected_revenue": 11.655
    },
    {
      "product_name": "HR Management System",
      "recommended_price": 316.35,
      "confidence": 0.6969,
      "tier": "enterprise",
      "segment": "enterprise",
      "conversion_probability": 0.35,
      "expected_revenue": 11.655
    },
    {
      "product_name": "Cybersecurity Platform",
      "recommended_price": 419.78,
      "confidence": 0.672,
      "tier": "enterprise",
      "segment": "enterprise",
      "conversion_probability": 0.35,
      "expected_revenue": 11.655
    },
    {
      "product_name": "Data Warehouse Solution",
      "recommended_price": 469.33,
      "confidence": 0.6767,
      "tier": "enterprise",
      "segment": "enterprise",
      "conversion_probability": 0.35,
      "expected_revenue": 11.655
    },
    {
      "product_name": "Security Information Manager",
      "recommended_price": 329.3,
      "confidence": 0.7164,
      "tier": "enterprise",
      "segment": "enterprise",
      "conversion_probability": 0.35,
      "expected_revenue": 11.655
    },
    {
      "product_name": "Business Intelligence Tool",
      "recommended_price": 350.41,
      "confidence": 0.7356,
      "tier": "enterprise",
      "segment": "enterprise",
      "conversion_probability": 0.35,
      "expected_revenue": 11.655
    },
    {
      "product_name": "Cloud Project Management",
      "recommended_price": 286.26,
      "confidence": 0.773,
      "tier": "enterprise",
      "segment": "enterprise",
      "conversion_probability": 0.35,
      "expected_revenue": 11.655
    },
    {
      "product_name": "Contract Management",
      "recommended_price": 262.9,
      "confidence": 0.681,
      "tier": "enterprise",
      "segment": "enterprise",
      "conversion_probability": 0.35,
      "expected_revenue": 11.655
    },
    {
      "product_name": "Cloud Migration Tool",
      "recommended_price": 369.99,
      "confidence": 0.7223,
      "tier": "enterprise",
      "segment": "enterprise",
      "conversion_probability": 0.35,
      "expected_revenue": 11.655
    },
    {
      "product_name": "Marketing Platform",
      "recommended_price": 217.82,
      "confidence": 0.7101,
      "tier": "growth",
      "segment": "mid-market",
      "conversion_probability": 0.25,
      "expected_revenue": 1.6583
    },
    {
      "product_name": "Video Conferencing Pro",
      "recommended_price": 195.31,
      "confidence": 0.7223,
      "tier": "growth",
      "segment": "mid-market",
      "conversion_probability": 0.25,
      "expected_revenue": 1.6583
    },
    {
      "product_name": "Email Marketing Suite",
      "recommended_price": 179.95,
      "confidence": 0.7177,
      "tier": "growth",
      "segment": "mid-market",
      "conversion_probability": 0.25,
      "expected_revenue": 1.6583
    },
    {
      "product_name": "Learning Management System",
      "recommended_price": 226.15,
      "confidence": 0.7136,
      "tier": "growth",
      "segment": "mid-market",
      "conversion_probability": 0.25,
      "expected_revenue": 1.6583
    },
    {
      "product_name": "E-commerce Platform",
      "recommended_price": 227.25,
      "confidence": 0.7206,
      "tier": "growth",
      "segment": "mid-market",
      "conversion_probability": 0.25,
      "expected_revenue": 1.6583
    },
    {
      "product_name": "DevOps Automation Tool",
      "recommended_price": 248.75,
      "confidence": 0.7219,
      "tier": "growth",
      "segment": "mid-market",
      "conversion_probability": 0.25,
      "expected_revenue": 1.6583
    },
    {
      "product_name": "IT Service Management",
      "recommended_price": 214.3,
      "confidence": 0.7424,
      "tier": "growth",
      "segment": "mid-market",
      "conversion_probability": 0.25,
      "expected_revenue": 1.6583
    },
    {
      "product_name": "Product Analytics Platform",
      "recommended_price": 207.91,
      "confidence": 0.744,
      "tier": "growth",
      "segment": "mid-market",
      "conversion_probability": 0.25,
      "expected_revenue": 1.6583
    }
  ],
  "dry_run": false
}
