{
  "idea_id": "idea-saas-pricing-intelligence",
  "timestamp": "2026-03-10T10:16:46.589747+00:00",
  "analyses_generated": 20,
  "revenue": 153.1267,
  "cost": 0.1,
  "projected_monthly_revenue": 4593.8,
  "results": [
    {
      "product_name": "Enterprise CRM",
      "recommended_price": 325.57,
      "confidence": 0.7252,
      "tier": "enterprise",
      "segment": "enterprise",
      "conversion_probability": 0.35,
      "expected_revenue": 11.655
    },
    {
      "product_name": "API Management Platform",
      "recommended_price": 337.13,
      "confidence": 0.7198,
      "tier": "enterprise",
      "segment": "enterprise",
      "conversion_probability": 0.35,
      "expected_revenue": 11.655
    },
    {
      "product_name": "Identity Management",
      "recommended_price": 327.03,
      "confidence": 0.6866,
      "tier": "enterprise",
      "segment": "enterprise",
      "conversion_probability": 0.35,
      "expected_revenue": 11.655
    },
    {
      "product_name": "Customer Data Platform",
      "recommended_price": 392.91,
      "confidence": 0.7218,
      "tier": "enterprise",
      "segment": "enterprise",
      "conversion_probability": 0.35,
      "expected_revenue": 11.655
    },
    {
      "product_name": "HR Management System",
      "recommended_price": 308.82,
      "confidence": 0.7443,
      "tier": "enterprise",
      "segment": "enterprise",
      "conversion_probability": 0.35,
      "expected_revenue": 11.655
    },
    {
      "product_name": "Cybersecurity Platform",
      "recommended_price": 420.69,
      "confidence": 0.7014,
      "tier": "enterprise",
      "segment": "enterprise",
      "conversion_probability": 0.35,
      "expected_revenue": 11.655
    },
    {
      "product_name": "Data Warehouse Solution",
      "recommended_price": 454.43,
      "confidence": 0.7982,
      "tier": "enterprise",
      "segment": "enterprise",
      "conversion_probability": 0.35,
      "expected_revenue": 11.655
    },
    {
      "product_name": "Security Information Manager",
      "recommended_price": 320.66,
      "confidence": 0.7248,
      "tier": "enterprise",
      "segment": "enterprise",
      "conversion_probability": 0.35,
      "expected_revenue": 11.655
    },
    {
      "product_name": "Business Intelligence Tool",
      "recommended_price": 332.01,
      "confidence": 0.7689,
      "tier": "enterprise",
      "segment": "enterprise",
      "conversion_probability": 0.35,
      "expected_revenue": 11.655
    },
    {
      "product_name": "Cloud Project Management",
      "recommended_price": 251.86,
      "confidence": 0.6935,
      "tier": "enterprise",
      "segment": "enterprise",
      "conversion_probability": 0.35,
      "expected_revenue": 11.655
    },
    {
      "product_name": "Contract Management",
      "recommended_price": 283.37,
      "confidence": 0.7404,
      "tier": "enterprise",
      "segment": "enterprise",
      "conversion_probability": 0.35,
      "expected_revenue": 11.655
    },
    {
      "product_name": "Cloud Migration Tool",
      "recommended_price": 354.58,
      "confidence": 0.7722,
      "tier": "enterprise",
      "segment": "enterprise",
      "conversion_probability": 0.35,
      "expected_revenue": 11.655
    },
    {
      "product_name": "Marketing Platform",
      "recommended_price": 197.63,
      "confidence": 0.7572,
      "tier": "growth",
      "segment": "mid-market",
      "conversion_probability": 0.25,
      "expected_revenue": 1.6583
    },
    {
      "product_name": "Video Conferencing Pro",
      "recommended_price": 177.71,
      "confidence": 0.6822,
      "tier": "growth",
      "segment": "mid-market",
      "conversion_probability": 0.25,
      "expected_revenue": 1.6583
    },
    {
      "product_name": "Email Marketing Suite",
      "recommended_price": 174.21,
      "confidence": 0.7527,
      "tier": "growth",
      "segment": "mid-market",
      "conversion_probability": 0.25,
      "expected_revenue": 1.6583
    },
    {
      "product_name": "Learning Management System",
      "recommended_price": 244.56,
      "confidence": 0.7798,
      "tier": "growth",
      "segment": "mid-market",
      "conversion_probability": 0.25,
      "expected_revenue": 1.6583
    },
    {
      "product_name": "E-commerce Platform",
      "recommended_price": 240.31,
      "confidence": 0.784,
      "tier": "growth",
      "segment": "mid-market",
      "conversion_probability": 0.25,
      "expected_revenue": 1.6583
    },
    {
      "product_name": "DevOps Automation Tool",
      "recommended_price": 207.94,
      "confidence": 0.7645,
      "tier": "growth",
      "segment": "mid-market",
      "conversion_probability": 0.25,
      "expected_revenue": 1.6583
    },
    {
      "product_name": "IT Service Management",
      "recommended_price": 225.38,
      "confidence": 0.7079,
      "tier": "growth",
      "segment": "mid-market",
      "conversion_probability": 0.25,
      "expected_revenue": 1.6583
    },
    {
      "product_name": "Product Analytics Platform",
      "recommended_price": 199.55,
      "confidence": 0.772,
      "tier": "growth",
      "segment": "mid-market",
      "conversion_probability": 0.25,
      "expected_revenue": 1.6583
    }
  ],
  "dry_run": false
}
