{
  "idea_id": "idea-saas-pricing-intelligence",
  "timestamp": "2026-03-10T05:24:09.163167+00:00",
  "analyses_generated": 20,
  "revenue": 153.1267,
  "cost": 0.1,
  "projected_monthly_revenue": 4593.8,
  "results": [
    {
      "product_name": "Enterprise CRM",
      "recommended_price": 316.9,
      "confidence": 0.753,
      "tier": "enterprise",
      "segment": "enterprise",
      "conversion_probability": 0.35,
      "expected_revenue": 11.655
    },
    {
      "product_name": "API Management Platform",
      "recommended_price": 362.5,
      "confidence": 0.7148,
      "tier": "enterprise",
      "segment": "enterprise",
      "conversion_probability": 0.35,
      "expected_revenue": 11.655
    },
    {
      "product_name": "Identity Management",
      "recommended_price": 295.09,
      "confidence": 0.7983,
      "tier": "enterprise",
      "segment": "enterprise",
      "conversion_probability": 0.35,
      "expected_revenue": 11.655
    },
    {
      "product_name": "Customer Data Platform",
      "recommended_price": 411.66,
      "confidence": 0.7491,
      "tier": "enterprise",
      "segment": "enterprise",
      "conversion_probability": 0.35,
      "expected_revenue": 11.655
    },
    {
      "product_name": "HR Management System",
      "recommended_price": 310.99,
      "confidence": 0.7666,
      "tier": "enterprise",
      "segment": "enterprise",
      "conversion_probability": 0.35,
      "expected_revenue": 11.655
    },
    {
      "product_name": "Cybersecurity Platform",
      "recommended_price": 358.46,
      "confidence": 0.7791,
      "tier": "enterprise",
      "segment": "enterprise",
      "conversion_probability": 0.35,
      "expected_revenue": 11.655
    },
    {
      "product_name": "Data Warehouse Solution",
      "recommended_price": 458.85,
      "confidence": 0.7477,
      "tier": "enterprise",
      "segment": "enterprise",
      "conversion_probability": 0.35,
      "expected_revenue": 11.655
    },
    {
      "product_name": "Security Information Manager",
      "recommended_price": 355.31,
      "confidence": 0.6793,
      "tier": "enterprise",
      "segment": "enterprise",
      "conversion_probability": 0.35,
      "expected_revenue": 11.655
    },
    {
      "product_name": "Business Intelligence Tool",
      "recommended_price": 318.53,
      "confidence": 0.7026,
      "tier": "enterprise",
      "segment": "enterprise",
      "conversion_probability": 0.35,
      "expected_revenue": 11.655
    },
    {
      "product_name": "Cloud Project Management",
      "recommended_price": 295.22,
      "confidence": 0.7144,
      "tier": "enterprise",
      "segment": "enterprise",
      "conversion_probability": 0.35,
      "expected_revenue": 11.655
    },
    {
      "product_name": "Contract Management",
      "recommended_price": 264.36,
      "confidence": 0.7581,
      "tier": "enterprise",
      "segment": "enterprise",
      "conversion_probability": 0.35,
      "expected_revenue": 11.655
    },
    {
      "product_name": "Cloud Migration Tool",
      "recommended_price": 363.04,
      "confidence": 0.7514,
      "tier": "enterprise",
      "segment": "enterprise",
      "conversion_probability": 0.35,
      "expected_revenue": 11.655
    },
    {
      "product_name": "Marketing Platform",
      "recommended_price": 213.01,
      "confidence": 0.6783,
      "tier": "growth",
      "segment": "mid-market",
      "conversion_probability": 0.25,
      "expected_revenue": 1.6583
    },
    {
      "product_name": "Video Conferencing Pro",
      "recommended_price": 199.45,
      "confidence": 0.7163,
      "tier": "growth",
      "segment": "mid-market",
      "conversion_probability": 0.25,
      "expected_revenue": 1.6583
    },
    {
      "product_name": "Email Marketing Suite",
      "recommended_price": 198.72,
      "confidence": 0.7412,
      "tier": "growth",
      "segment": "mid-market",
      "conversion_probability": 0.25,
      "expected_revenue": 1.6583
    },
    {
      "product_name": "Learning Management System",
      "recommended_price": 233.25,
      "confidence": 0.7561,
      "tier": "growth",
      "segment": "mid-market",
      "conversion_probability": 0.25,
      "expected_revenue": 1.6583
    },
    {
      "product_name": "E-commerce Platform",
      "recommended_price": 251.89,
      "confidence": 0.7438,
      "tier": "growth",
      "segment": "mid-market",
      "conversion_probability": 0.25,
      "expected_revenue": 1.6583
    },
    {
      "product_name": "DevOps Automation Tool",
      "recommended_price": 228.81,
      "confidence": 0.7587,
      "tier": "growth",
      "segment": "mid-market",
      "conversion_probability": 0.25,
      "expected_revenue": 1.6583
    },
    {
      "product_name": "IT Service Management",
      "recommended_price": 216.12,
      "confidence": 0.7499,
      "tier": "growth",
      "segment": "mid-market",
      "conversion_probability": 0.25,
      "expected_revenue": 1.6583
    },
    {
      "product_name": "Product Analytics Platform",
      "recommended_price": 206.77,
      "confidence": 0.725,
      "tier": "growth",
      "segment": "mid-market",
      "conversion_probability": 0.25,
      "expected_revenue": 1.6583
    }
  ],
  "dry_run": false
}
